seed_services_cli/__init__.py
seed_services_cli/auth.py
seed_services_cli/ci.py
seed_services_cli/hub.py
seed_services_cli/identity_store.py
seed_services_cli/main.py
seed_services_cli/stage_based_messaging.py
seed_services_cli/tests/__init__.py
seed_services_cli/tests/test_auth.py
seed_services_cli/tests/test_ci.py
seed_services_cli/tests/test_hub.py
seed_services_cli/tests/test_identity_store.py
seed_services_cli/tests/test_main.py
seed_services_cli/tests/test_stage_based_messaging.py
seed_services_cli-0.0.13.dist-info/AUTHORS
seed_services_cli-0.0.13.dist-info/LICENSE
seed_services_cli-0.0.13.dist-info/METADATA
seed_services_cli-0.0.13.dist-info/WHEEL
seed_services_cli-0.0.13.dist-info/entry_points.txt
seed_services_cli-0.0.13.dist-info/top_level.txt
seed_services_cli-0.0.13.dist-info/RECORD
