Metadata-Version: 2.1
Name: seed-services-cli
Version: 0.0.13
Summary: A command-line interface for Seed Services HTTP APIs
Home-page: http://github.com/praekelt/seed-services-cli
Author: Praekelt Foundation and Individual Contributors
Author-email: support@praekeltfoundation.com
License: BSD
Platform: UNKNOWN
Classifier: Development Status :: 4 - Beta
Classifier: Intended Audience :: Developers
Classifier: License :: OSI Approved :: BSD License
Classifier: Operating System :: POSIX
Classifier: Programming Language :: Python
Requires-Dist: click
Requires-Dist: click-config
Requires-Dist: seed-services-client (==0.37.0)
Requires-Dist: demands (==3.0.0)
